{
  "usergraph": {
    "Willy": [
      "Melina", 
      "Juliana", 
      "Madella", 
      "Jerrilee", 
      "Binni", 
      "Amalita", 
      "Alicea"
    ], 
    "Dorette": [
      "Fernande", 
      "Aurore", 
      "Robinetta", 
      "Marji", 
      "Madella", 
      "Myriam"
    ], 
    "Kaitlyn": [
      "Fernande", 
      "Anthia", 
      "Sofia", 
      "Gillie", 
      "Lucia", 
      "Cybil", 
      "Dorene", 
      "Shirlene", 
      "Gracia", 
      "George"
    ], 
    "Sharia": [
      "Yolande", 
      "Quentin", 
      "George", 
      "Wendy"
    ], 
    "Genevieve": [
      "Cristabel", 
      "Madella", 
      "Glad", 
      "Carina"
    ], 
    "Brigitta": [
      "Kati", 
      "Dee", 
      "Aurore"
    ], 
    "Christa": [
      "Rosalinda", 
      "Quentin", 
      "Hilary", 
      "Philomena", 
      "Christa", 
      "Tessa", 
      "Marcellina", 
      "Gracia", 
      "Amalita"
    ], 
    "Amalita": [
      "Willy", 
      "Dianne", 
      "Harley", 
      "Monika", 
      "Christa", 
      "Jeannie"
    ], 
    "Chantal": [
      "Georgianna", 
      "Shirlene"
    ], 
    "Christiane": [
      "Nettle", 
      "Magdalena", 
      "Harley"
    ], 
    "Yolande": [
      "Jerrilee", 
      "Melina", 
      "Sharia", 
      "Georgianna", 
      "Phedra", 
      "Revkah", 
      "Kirsten"
    ], 
    "Gillie": [
      "Dorene", 
      "Tessa", 
      "Anabella", 
      "Kaitlyn"
    ], 
    "Dorene": [
      "Tonia", 
      "Kaitlyn", 
      "Kathleen", 
      "Quentin", 
      "Gillie", 
      "Revkah", 
      "Gracia", 
      "Jeannie"
    ], 
    "Olive": [
      "Bab", 
      "George", 
      "Sharron", 
      "Harley"
    ], 
    "Ange": [
      "Edna", 
      "Cristabel", 
      "Sal", 
      "Dee", 
      "Dianne"
    ], 
    "Harley": [
      "Tonia", 
      "Blakelee", 
      "Christiane", 
      "Fernande", 
      "Melita", 
      "Robinetta", 
      "Cybil", 
      "Olive", 
      "Monika", 
      "Lucia", 
      "Amalita", 
      "Alicea"
    ], 
    "Nettle": [
      "Sofia", 
      "Carina", 
      "Christiane", 
      "Aurie", 
      "Aurore", 
      "Edna", 
      "Bab", 
      "Revkah"
    ], 
    "Cybil": [
      "Maribel", 
      "Arlen", 
      "Dianne", 
      "Kaitlyn", 
      "Harley", 
      "Conny", 
      "Bab", 
      "Sharron", 
      "George", 
      "Hanny"
    ], 
    "Magdalena": [
      "Christiane", 
      "Jeannie", 
      "Rosalinda"
    ], 
    "Arlen": [
      "Theo", 
      "Juliana", 
      "Aurie", 
      "Ginevra", 
      "Cybil", 
      "Gracia"
    ], 
    "Eba": [
      "Rebekah", 
      "Robbie", 
      "Marcela", 
      "Tessa"
    ], 
    "Melina": [
      "Willy", 
      "Maribel", 
      "Yolande", 
      "Asia", 
      "Conny", 
      "Isobel"
    ], 
    "Sal": [
      "Ange", 
      "Rosalinda", 
      "Shea"
    ], 
    "Anestassia": [
      "Conny", 
      "Georgianna", 
      "George", 
      "Asia", 
      "Shea"
    ], 
    "Robinetta": [
      "Dorette", 
      "Shea", 
      "Catherine", 
      "Hilary", 
      "Aurore", 
      "Harley"
    ], 
    "Kati": [
      "Brigitta", 
      "Fiorenze", 
      "Carina"
    ], 
    "Cristabel": [
      "Edna", 
      "Ange", 
      "Glad", 
      "Marcela", 
      "Genevieve"
    ], 
    "Georgianna": [
      "Chantal", 
      "Dianne", 
      "Lianna", 
      "Yolande", 
      "Anestassia", 
      "Bab", 
      "Kailey", 
      "Alicea"
    ], 
    "Eadith": [
      "Aurore", 
      "Rosalinda", 
      "Phedra", 
      "Kailey"
    ], 
    "George": [
      "Kaitlyn", 
      "Sharia", 
      "Anestassia", 
      "Cybil", 
      "Olive", 
      "Fiorenze"
    ], 
    "Karlen": [
      "Sofia", 
      "Marji", 
      "Anabella", 
      "Binni", 
      "Monika", 
      "Gracia"
    ], 
    "Hilary": [
      "Letisha", 
      "Carina", 
      "Philomena", 
      "Robinetta", 
      "Drusie", 
      "Christa", 
      "Fiorenze", 
      "Hanny"
    ], 
    "Iolanthe": [
      "Theo", 
      "Rosalinda", 
      "Shea", 
      "Aurie", 
      "Melitta", 
      "Wendy", 
      "Kitti", 
      "Fiorenze"
    ], 
    "Sharron": [
      "Olive", 
      "Binni", 
      "Aurie", 
      "Cybil", 
      "Melitta"
    ], 
    "Kailey": [
      "Eadith", 
      "Georgianna", 
      "Philomena", 
      "Asia", 
      "Myriam"
    ], 
    "Letisha": [
      "Rebekah", 
      "Sascha", 
      "Jerrilee", 
      "Hilary"
    ], 
    "Lianna": [
      "Alicea", 
      "Georgianna", 
      "Catherine", 
      "Dianne", 
      "Sascha"
    ], 
    "Fernande": [
      "Robbie", 
      "Dorette", 
      "Kaitlyn", 
      "Veronique", 
      "Philomena", 
      "Harley", 
      "Asia", 
      "Alicea"
    ], 
    "Marji": [
      "Karlen", 
      "Kitti", 
      "Robbie", 
      "Dorette"
    ], 
    "Aurore": [
      "Dorette", 
      "Edna", 
      "Asia", 
      "Robinetta", 
      "Nettle", 
      "Tessa", 
      "Eadith", 
      "Brigitta", 
      "Marcela"
    ], 
    "Marguerite": [
      "Anthia", 
      "Quentin", 
      "Kitti"
    ], 
    "Phedra": [
      "Marcellina", 
      "Eadith", 
      "Yolande"
    ], 
    "Sascha": [
      "Tonia", 
      "Maribel", 
      "Dianne", 
      "Letisha", 
      "Lianna", 
      "Lucia"
    ], 
    "Alicea": [
      "Willy", 
      "Ginevra", 
      "Robbie", 
      "Fernande", 
      "Lianna", 
      "Aurie", 
      "Harley", 
      "Georgianna"
    ], 
    "Maribel": [
      "Melina", 
      "Blakelee", 
      "Jeannie", 
      "Melita", 
      "Cybil", 
      "Sascha"
    ], 
    "Neila": [
      "Cindelyn", 
      "Binni", 
      "Veronique"
    ], 
    "Dianne": [
      "Ange", 
      "Shea", 
      "Cindelyn", 
      "Lianna", 
      "Philomena", 
      "Bab", 
      "Georgianna", 
      "Cybil", 
      "Binni", 
      "Amalita", 
      "Sascha"
    ], 
    "Rosalinda": [
      "Theo", 
      "Sal", 
      "Iolanthe", 
      "Christa", 
      "Madella", 
      "Eadith", 
      "Magdalena"
    ], 
    "Shirlene": [
      "Chantal", 
      "Robbie", 
      "Kaitlyn", 
      "Blakelee", 
      "Anabella", 
      "Marcellina", 
      "Kirsten", 
      "Fiorenze"
    ], 
    "Fiorenze": [
      "Hilary", 
      "Iolanthe", 
      "Kati", 
      "Asia", 
      "Shirlene", 
      "Revkah", 
      "George", 
      "Glad"
    ], 
    "Ginevra": [
      "Madella", 
      "Arlen", 
      "Tessa", 
      "Asia", 
      "Alicea"
    ], 
    "Shea": [
      "Dianne", 
      "Sal", 
      "Kathleen", 
      "Quentin", 
      "Anestassia", 
      "Robinetta", 
      "Iolanthe", 
      "Wendy", 
      "Myriam", 
      "Glad"
    ], 
    "Juliana": [
      "Willy", 
      "Anthia", 
      "Gracia", 
      "Valaree", 
      "Arlen"
    ], 
    "Catherine": [
      "Valaree", 
      "Lianna", 
      "Robinetta", 
      "Wendy", 
      "Jeannie", 
      "Glad"
    ], 
    "Aurie": [
      "Arlen", 
      "Iolanthe", 
      "Nettle", 
      "Tessa", 
      "Sharron", 
      "Alicea"
    ], 
    "Valaree": [
      "Blakelee", 
      "Edna", 
      "Juliana", 
      "Catherine", 
      "Asia", 
      "Marcellina"
    ], 
    "Anthia": [
      "Monika", 
      "Juliana", 
      "Marguerite", 
      "Wendy", 
      "Kaitlyn"
    ], 
    "Asia": [
      "Ginevra", 
      "Valaree", 
      "Melina", 
      "Fernande", 
      "Anestassia", 
      "Aurore", 
      "Binni", 
      "Fiorenze", 
      "Kailey"
    ], 
    "Conny": [
      "Melina", 
      "Blakelee", 
      "Anestassia", 
      "Melitta", 
      "Cybil", 
      "Kirsten"
    ], 
    "Melitta": [
      "Carina", 
      "Blakelee", 
      "Iolanthe", 
      "Lucia", 
      "Conny", 
      "Sharron"
    ], 
    "Basia": [
      "Myriam", 
      "Jeannie"
    ], 
    "Marcellina": [
      "Shirlene", 
      "Valaree", 
      "Christa", 
      "Bab", 
      "Phedra", 
      "Marcela"
    ], 
    "Myriam": [
      "Dorette", 
      "Shea", 
      "Veronique", 
      "Basia", 
      "Wendy", 
      "Kailey"
    ], 
    "Tonia": [
      "Dorene", 
      "Sascha", 
      "Harley"
    ], 
    "Cindelyn": [
      "Edna", 
      "Neila", 
      "Dianne"
    ], 
    "Kitti": [
      "Marguerite", 
      "Kathleen", 
      "Iolanthe", 
      "Jeannie", 
      "Marji", 
      "Bunny"
    ], 
    "Jeannie": [
      "Maribel", 
      "Basia", 
      "Kitti", 
      "Catherine", 
      "Lucia", 
      "Dorene", 
      "Amalita", 
      "Magdalena"
    ], 
    "Anabella": [
      "Robbie", 
      "Carina", 
      "Karlen", 
      "Gillie", 
      "Shirlene", 
      "Isobel"
    ], 
    "Rebekah": [
      "Letisha", 
      "Eba", 
      "Quentin", 
      "Philomena", 
      "Janetta", 
      "Gracia"
    ], 
    "Dee": [
      "Ange", 
      "Brigitta", 
      "Marcela"
    ], 
    "Kirsten": [
      "Conny", 
      "Yolande", 
      "Shirlene", 
      "Jerrilee"
    ], 
    "Philomena": [
      "Rebekah", 
      "Dianne", 
      "Fernande", 
      "Hilary", 
      "Christa", 
      "Kailey"
    ], 
    "Madella": [
      "Willy", 
      "Ginevra", 
      "Rosalinda", 
      "Dorette", 
      "Edna", 
      "Genevieve", 
      "Carina"
    ], 
    "Tessa": [
      "Aurie", 
      "Ginevra", 
      "Eba", 
      "Sofia", 
      "Gillie", 
      "Aurore", 
      "Christa"
    ], 
    "Veronique": [
      "Fernande", 
      "Neila", 
      "Myriam", 
      "Lucia"
    ], 
    "Wendy": [
      "Ladonna", 
      "Shea", 
      "Sharia", 
      "Anthia", 
      "Sofia", 
      "Catherine", 
      "Iolanthe", 
      "Edna", 
      "Jerrilee", 
      "Myriam"
    ], 
    "Carina": [
      "Melitta", 
      "Hilary", 
      "Genevieve", 
      "Nettle", 
      "Kati", 
      "Madella", 
      "Anabella", 
      "Drusie"
    ], 
    "Kathleen": [
      "Kitti", 
      "Dorene", 
      "Shea"
    ], 
    "Isobel": [
      "Binni", 
      "Revkah", 
      "Melina", 
      "Anabella", 
      "Blakelee"
    ], 
    "Bunny": [
      "Bab", 
      "Kitti"
    ], 
    "Ladonna": [
      "Gracia", 
      "Wendy"
    ], 
    "Quentin": [
      "Rebekah", 
      "Marguerite", 
      "Shea", 
      "Sharia", 
      "Christa", 
      "Dorene", 
      "Gracia"
    ], 
    "Lucia": [
      "Kaitlyn", 
      "Veronique", 
      "Jeannie", 
      "Melitta", 
      "Harley", 
      "Sascha"
    ], 
    "Jerrilee": [
      "Willy", 
      "Letisha", 
      "Yolande", 
      "Wendy", 
      "Drusie", 
      "Kirsten"
    ], 
    "Monika": [
      "Karlen", 
      "Anthia", 
      "Amalita", 
      "Robbie", 
      "Harley"
    ], 
    "Glad": [
      "Cristabel", 
      "Genevieve", 
      "Catherine", 
      "Fiorenze", 
      "Shea"
    ], 
    "Theo": [
      "Arlen", 
      "Iolanthe", 
      "Rosalinda", 
      "Gracia"
    ], 
    "Robbie": [
      "Eba", 
      "Fernande", 
      "Marji", 
      "Melita", 
      "Shirlene", 
      "Monika", 
      "Anabella", 
      "Alicea"
    ], 
    "Blakelee": [
      "Maribel", 
      "Valaree", 
      "Harley", 
      "Conny", 
      "Melitta", 
      "Shirlene", 
      "Isobel", 
      "Gracia"
    ], 
    "Binni": [
      "Willy", 
      "Neila", 
      "Dianne", 
      "Karlen", 
      "Asia", 
      "Sharron", 
      "Isobel"
    ], 
    "Janetta": [
      "Rebekah"
    ], 
    "Marcela": [
      "Eba", 
      "Aurore", 
      "Cristabel", 
      "Revkah", 
      "Marcellina", 
      "Dee"
    ], 
    "Hanny": [
      "Cybil", 
      "Melita", 
      "Hilary"
    ], 
    "Edna": [
      "Ange", 
      "Valaree", 
      "Cindelyn", 
      "Aurore", 
      "Nettle", 
      "Cristabel", 
      "Madella", 
      "Wendy"
    ], 
    "Sofia": [
      "Nettle", 
      "Karlen", 
      "Tessa", 
      "Wendy", 
      "Kaitlyn"
    ], 
    "Melita": [
      "Maribel", 
      "Hanny", 
      "Robbie", 
      "Harley"
    ], 
    "Revkah": [
      "Yolande", 
      "Nettle", 
      "Fiorenze", 
      "Isobel", 
      "Marcela", 
      "Dorene"
    ], 
    "Bab": [
      "Dianne", 
      "Nettle", 
      "Olive", 
      "Georgianna", 
      "Cybil", 
      "Marcellina", 
      "Gracia", 
      "Bunny"
    ], 
    "Drusie": [
      "Carina", 
      "Hilary", 
      "Jerrilee"
    ], 
    "Gracia": [
      "Theo", 
      "Ladonna", 
      "Arlen", 
      "Kaitlyn", 
      "Karlen", 
      "Juliana", 
      "Quentin", 
      "Christa", 
      "Rebekah", 
      "Bab", 
      "Dorene", 
      "Blakelee"
    ]
  }, 
  "resources": [
    {
      "controller": "Hilary", 
      "name": "Afghanistan", 
      "target": [
        "Marcellina", 
        "Isobel", 
        "Anabella"
      ]
    }, 
    {
      "controller": "Yolande", 
      "name": "Aland Islands", 
      "target": [
        "Asia"
      ]
    }, 
    {
      "controller": "Anestassia", 
      "name": "Albania", 
      "target": [
        "Lianna", 
        "Jeannie"
      ]
    }, 
    {
      "controller": "Cristabel", 
      "name": "Algeria", 
      "target": []
    }, 
    {
      "controller": "Phedra", 
      "name": "American Samoa", 
      "target": [
        "Christa"
      ]
    }, 
    {
      "controller": "Alicea", 
      "name": "Andorra", 
      "target": []
    }, 
    {
      "controller": "Asia", 
      "name": "Angola", 
      "target": []
    }, 
    {
      "controller": "Theo", 
      "name": "Anguilla", 
      "target": [
        "Kathleen", 
        "Janetta", 
        "Aurore"
      ]
    }, 
    {
      "controller": "Sharron", 
      "name": "Antarctica", 
      "target": [
        "Dianne"
      ]
    }, 
    {
      "controller": "Philomena", 
      "name": "Antigua and Barbuda", 
      "target": []
    }, 
    {
      "controller": "Maribel", 
      "name": "Argentina", 
      "target": []
    }, 
    {
      "controller": "Robinetta", 
      "name": "Armenia", 
      "target": [
        "Shea"
      ]
    }, 
    {
      "controller": "Ange", 
      "name": "Aruba", 
      "target": [
        "Christiane", 
        "Marcela"
      ]
    }, 
    {
      "controller": "Maribel", 
      "name": "Australia", 
      "target": [
        "Madella", 
        "Hilary", 
        "Kaitlyn"
      ]
    }, 
    {
      "controller": "Marji", 
      "name": "Austria", 
      "target": []
    }, 
    {
      "controller": "Gillie", 
      "name": "Azerbaijan", 
      "target": [
        "Conny", 
        "Ginevra"
      ]
    }, 
    {
      "controller": "Ladonna", 
      "name": "Bahamas", 
      "target": [
        "Kaitlyn"
      ]
    }, 
    {
      "controller": "Valaree", 
      "name": "Bahrain", 
      "target": [
        "Kati", 
        "Glad", 
        "Kaitlyn"
      ]
    }, 
    {
      "controller": "Drusie", 
      "name": "Bangladesh", 
      "target": [
        "Melitta", 
        "Sofia"
      ]
    }, 
    {
      "controller": "Eadith", 
      "name": "Barbados", 
      "target": [
        "Theo"
      ]
    }, 
    {
      "controller": "Fiorenze", 
      "name": "Belarus", 
      "target": [
        "Lianna"
      ]
    }, 
    {
      "controller": "Robinetta", 
      "name": "Belgium", 
      "target": [
        "Olive", 
        "Shirlene"
      ]
    }, 
    {
      "controller": "Theo", 
      "name": "Belize", 
      "target": []
    }, 
    {
      "controller": "Marji", 
      "name": "Benin", 
      "target": [
        "Philomena", 
        "Fernande"
      ]
    }, 
    {
      "controller": "Neila", 
      "name": "Bermuda", 
      "target": [
        "Anthia", 
        "Quentin"
      ]
    }, 
    {
      "controller": "Phedra", 
      "name": "Bhutan", 
      "target": [
        "Eadith", 
        "Janetta", 
        "Chantal"
      ]
    }, 
    {
      "controller": "Bunny", 
      "name": "Bolivia", 
      "target": []
    }, 
    {
      "controller": "Amalita", 
      "name": "Bosnia and Herzegovina", 
      "target": [
        "Drusie", 
        "Catherine"
      ]
    }, 
    {
      "controller": "Georgianna", 
      "name": "Botswana", 
      "target": [
        "Binni"
      ]
    }, 
    {
      "controller": "Marcellina", 
      "name": "Bouvet Island", 
      "target": [
        "Sharron"
      ]
    }, 
    {
      "controller": "Yolande", 
      "name": "Brazil", 
      "target": []
    }, 
    {
      "controller": "Madella", 
      "name": "British Indian Ocean Territory", 
      "target": []
    }, 
    {
      "controller": "Maribel", 
      "name": "Brunei Darussalam", 
      "target": [
        "Sal"
      ]
    }, 
    {
      "controller": "Jerrilee", 
      "name": "Bulgaria", 
      "target": [
        "Isobel", 
        "Chantal"
      ]
    }, 
    {
      "controller": "Glad", 
      "name": "Burkina Faso", 
      "target": [
        "Cindelyn"
      ]
    }, 
    {
      "controller": "Aurie", 
      "name": "Burundi", 
      "target": [
        "Ladonna", 
        "Letisha", 
        "Sharron"
      ]
    }, 
    {
      "controller": "Sofia", 
      "name": "Cambodia", 
      "target": []
    }, 
    {
      "controller": "Asia", 
      "name": "Cameroon", 
      "target": [
        "Lianna", 
        "Shea"
      ]
    }, 
    {
      "controller": "Sascha", 
      "name": "Canada", 
      "target": [
        "Cristabel"
      ]
    }, 
    {
      "controller": "Kailey", 
      "name": "Cape Verde", 
      "target": [
        "Rebekah", 
        "Anabella"
      ]
    }, 
    {
      "controller": "Robbie", 
      "name": "Cayman Islands", 
      "target": []
    }, 
    {
      "controller": "Gracia", 
      "name": "Central African Republic", 
      "target": []
    }, 
    {
      "controller": "Cybil", 
      "name": "Chad", 
      "target": [
        "Edna", 
        "Sharia", 
        "Robinetta"
      ]
    }, 
    {
      "controller": "Monika", 
      "name": "Chile", 
      "target": [
        "Sharia", 
        "Robbie"
      ]
    }, 
    {
      "controller": "Asia", 
      "name": "China", 
      "target": [
        "Marcellina"
      ]
    }, 
    {
      "controller": "Melitta", 
      "name": "Christmas Island", 
      "target": [
        "Carina"
      ]
    }, 
    {
      "controller": "Juliana", 
      "name": "Cocos (Keeling) Islands", 
      "target": [
        "Olive"
      ]
    }, 
    {
      "controller": "Fiorenze", 
      "name": "Colombia", 
      "target": []
    }, 
    {
      "controller": "Quentin", 
      "name": "Comoros", 
      "target": [
        "Georgianna", 
        "Aurore"
      ]
    }, 
    {
      "controller": "Melina", 
      "name": "Congo", 
      "target": [
        "Kirsten", 
        "Hanny"
      ]
    }, 
    {
      "controller": "Kirsten", 
      "name": "Congo, The Democratic Republic of the", 
      "target": [
        "Ladonna", 
        "Ange", 
        "Hilary"
      ]
    }
  ], 
  "users": [
    "Ladonna", 
    "Nettle", 
    "Yolande", 
    "Willy", 
    "Sharron", 
    "Iolanthe", 
    "Kailey", 
    "Brigitta", 
    "Wendy", 
    "Basia", 
    "Isobel", 
    "Ginevra", 
    "Binni", 
    "Sascha", 
    "George", 
    "Arlen", 
    "Amalita", 
    "Shirlene", 
    "Christa", 
    "Rosalinda", 
    "Karlen", 
    "Kathleen", 
    "Letisha", 
    "Alicea", 
    "Maribel", 
    "Sharia", 
    "Theo", 
    "Robbie", 
    "Catherine", 
    "Kati", 
    "Fiorenze", 
    "Philomena", 
    "Anabella", 
    "Ange", 
    "Bab", 
    "Genevieve", 
    "Cindelyn", 
    "Gracia", 
    "Valaree", 
    "Hilary", 
    "Olive", 
    "Cybil", 
    "Fernande", 
    "Aurore", 
    "Kirsten", 
    "Marguerite", 
    "Lucia", 
    "Dorette", 
    "Janetta", 
    "Juliana", 
    "Magdalena", 
    "Tessa", 
    "Jerrilee", 
    "Melina", 
    "Anthia", 
    "Dee", 
    "Dorene", 
    "Myriam", 
    "Glad", 
    "Edna", 
    "Hanny", 
    "Georgianna", 
    "Sal", 
    "Sofia", 
    "Monika", 
    "Dianne", 
    "Christiane", 
    "Neila", 
    "Tonia", 
    "Robinetta", 
    "Revkah", 
    "Conny", 
    "Melita", 
    "Quentin", 
    "Rebekah", 
    "Blakelee", 
    "Carina", 
    "Cristabel", 
    "Anestassia", 
    "Jeannie", 
    "Marcellina", 
    "Eba", 
    "Lianna", 
    "Bunny", 
    "Phedra", 
    "Chantal", 
    "Harley", 
    "Marji", 
    "Veronique", 
    "Asia", 
    "Gillie", 
    "Eadith", 
    "Madella", 
    "Marcela", 
    "Shea", 
    "Drusie", 
    "Melitta", 
    "Kitti", 
    "Aurie", 
    "Kaitlyn"
  ], 
  "policies": {
    "Willy": {
      "tup": "h=2", 
      "trp": "h>3"
    }, 
    "Dorette": {
      "tup": "h>1", 
      "trp": "h<2"
    }, 
    "Kaitlyn": {
      "tup": "h=1", 
      "trp": "h<3"
    }, 
    "Sharia": {
      "tup": "h=1", 
      "trp": "h<2"
    }, 
    "Genevieve": {
      "tup": "h=1", 
      "trp": "h=1"
    }, 
    "Brigitta": {
      "tup": "h=1", 
      "trp": "h=1"
    }, 
    "Christa": {
      "tup": "h=3", 
      "trp": "h>1"
    }, 
    "Amalita": {
      "tup": "h=3", 
      "trp": "h=1"
    }, 
    "Chantal": {
      "tup": "h>2", 
      "trp": "h=1"
    }, 
    "Christiane": {
      "tup": "h=3", 
      "trp": "h=3"
    }, 
    "Yolande": {
      "tup": "h>2", 
      "trp": "h>3"
    }, 
    "Gillie": {
      "tup": "h>2", 
      "trp": "h<3"
    }, 
    "Dorene": {
      "tup": "h>1", 
      "trp": "h>2"
    }, 
    "Olive": {
      "tup": "h<3", 
      "trp": "h>3"
    }, 
    "Ange": {
      "tup": "h<2", 
      "trp": "h>1"
    }, 
    "Harley": {
      "tup": "h>3", 
      "trp": "h<3"
    }, 
    "Nettle": {
      "tup": "h>2", 
      "trp": "h>2"
    }, 
    "Cybil": {
      "tup": "h>3", 
      "trp": "h=2"
    }, 
    "Magdalena": {
      "tup": "h<3", 
      "trp": "h=3"
    }, 
    "Arlen": {
      "tup": "h<1", 
      "trp": "h<3"
    }, 
    "Eba": {
      "tup": "h<1", 
      "trp": "h<1"
    }, 
    "Melina": {
      "tup": "h<1", 
      "trp": "h=3"
    }, 
    "Sal": {
      "tup": "h<2", 
      "trp": "h<1"
    }, 
    "Anestassia": {
      "tup": "h=3", 
      "trp": "h>2"
    }, 
    "Robinetta": {
      "tup": "h=1", 
      "trp": "h<3"
    }, 
    "Kati": {
      "tup": "h<3", 
      "trp": "h=1"
    }, 
    "Cristabel": {
      "tup": "h<1", 
      "trp": "h<3"
    }, 
    "Georgianna": {
      "tup": "h>2", 
      "trp": "h<2"
    }, 
    "Eadith": {
      "tup": "h=1", 
      "trp": "h<3"
    }, 
    "George": {
      "tup": "h<1", 
      "trp": "h=1"
    }, 
    "Karlen": {
      "tup": "h<1", 
      "trp": "h>2"
    }, 
    "Hilary": {
      "tup": "h>1", 
      "trp": "h>2"
    }, 
    "Iolanthe": {
      "tup": "h=3", 
      "trp": "h>1"
    }, 
    "Sharron": {
      "tup": "h=1", 
      "trp": "h<1"
    }, 
    "Kailey": {
      "tup": "h<3", 
      "trp": "h>1"
    }, 
    "Letisha": {
      "tup": "h=2", 
      "trp": "h<2"
    }, 
    "Lianna": {
      "tup": "h>3", 
      "trp": "h<1"
    }, 
    "Fernande": {
      "tup": "h>2", 
      "trp": "h<2"
    }, 
    "Marji": {
      "tup": "h>2", 
      "trp": "h>1"
    }, 
    "Aurore": {
      "tup": "h<2", 
      "trp": "h=2"
    }, 
    "Marguerite": {
      "tup": "h<3", 
      "trp": "h<2"
    }, 
    "Phedra": {
      "tup": "h<2", 
      "trp": "h=2"
    }, 
    "Sascha": {
      "tup": "h>1", 
      "trp": "h>1"
    }, 
    "Alicea": {
      "tup": "h<1", 
      "trp": "h>3"
    }, 
    "Maribel": {
      "tup": "h=3", 
      "trp": "h>3"
    }, 
    "Neila": {
      "tup": "h>2", 
      "trp": "h>1"
    }, 
    "Dianne": {
      "tup": "h<2", 
      "trp": "h>3"
    }, 
    "Rosalinda": {
      "tup": "h>1", 
      "trp": "h>2"
    }, 
    "Shirlene": {
      "tup": "h=1", 
      "trp": "h<2"
    }, 
    "Fiorenze": {
      "tup": "h<1", 
      "trp": "h>2"
    }, 
    "Ginevra": {
      "tup": "h<2", 
      "trp": "h<1"
    }, 
    "Shea": {
      "tup": "h=3", 
      "trp": "h=1"
    }, 
    "Juliana": {
      "tup": "h<2", 
      "trp": "h=1"
    }, 
    "Catherine": {
      "tup": "h<1", 
      "trp": "h=2"
    }, 
    "Aurie": {
      "tup": "h>1", 
      "trp": "h>1"
    }, 
    "Valaree": {
      "tup": "h<1", 
      "trp": "h=1"
    }, 
    "Anthia": {
      "tup": "h<2", 
      "trp": "h<1"
    }, 
    "Asia": {
      "tup": "h>2", 
      "trp": "h<2"
    }, 
    "Conny": {
      "tup": "h=3", 
      "trp": "h>1"
    }, 
    "Melitta": {
      "tup": "h>3", 
      "trp": "h>1"
    }, 
    "Basia": {
      "tup": "h=1", 
      "trp": "h<3"
    }, 
    "Marcellina": {
      "tup": "h<2", 
      "trp": "h=2"
    }, 
    "Myriam": {
      "tup": "h>3", 
      "trp": "h>3"
    }, 
    "Tonia": {
      "tup": "h<1", 
      "trp": "h>2"
    }, 
    "Cindelyn": {
      "tup": "h<2", 
      "trp": "h>3"
    }, 
    "Kitti": {
      "tup": "h=2", 
      "trp": "h=2"
    }, 
    "Jeannie": {
      "tup": "h<1", 
      "trp": "h=1"
    }, 
    "Anabella": {
      "tup": "h<1", 
      "trp": "h=2"
    }, 
    "Rebekah": {
      "tup": "h=3", 
      "trp": "h=1"
    }, 
    "Dee": {
      "tup": "h=3", 
      "trp": "h<2"
    }, 
    "Kirsten": {
      "tup": "h=3", 
      "trp": "h<1"
    }, 
    "Philomena": {
      "tup": "h<3", 
      "trp": "h=1"
    }, 
    "Madella": {
      "tup": "h<3", 
      "trp": "h<3"
    }, 
    "Tessa": {
      "tup": "h>2", 
      "trp": "h=1"
    }, 
    "Veronique": {
      "tup": "h>2", 
      "trp": "h>3"
    }, 
    "Wendy": {
      "tup": "h<2", 
      "trp": "h<2"
    }, 
    "Carina": {
      "tup": "h=1", 
      "trp": "h=1"
    }, 
    "Kathleen": {
      "tup": "h>1", 
      "trp": "h=1"
    }, 
    "Isobel": {
      "tup": "h>1", 
      "trp": "h<1"
    }, 
    "Bunny": {
      "tup": "h=1", 
      "trp": "h=3"
    }, 
    "Ladonna": {
      "tup": "h>1", 
      "trp": "h>1"
    }, 
    "Quentin": {
      "tup": "h<1", 
      "trp": "h>2"
    }, 
    "Lucia": {
      "tup": "h>3", 
      "trp": "h=3"
    }, 
    "Jerrilee": {
      "tup": "h>2", 
      "trp": "h<3"
    }, 
    "Monika": {
      "tup": "h=1", 
      "trp": "h>2"
    }, 
    "Glad": {
      "tup": "h>1", 
      "trp": "h=1"
    }, 
    "Theo": {
      "tup": "h=1", 
      "trp": "h=1"
    }, 
    "Robbie": {
      "tup": "h=1", 
      "trp": "h<3"
    }, 
    "Blakelee": {
      "tup": "h<2", 
      "trp": "h=1"
    }, 
    "Binni": {
      "tup": "h<3", 
      "trp": "h>1"
    }, 
    "Janetta": {
      "tup": "h<1", 
      "trp": "h>1"
    }, 
    "Marcela": {
      "tup": "h<2", 
      "trp": "h<2"
    }, 
    "Hanny": {
      "tup": "h=1", 
      "trp": "h=1"
    }, 
    "Edna": {
      "tup": "h>1", 
      "trp": "h=1"
    }, 
    "Sofia": {
      "tup": "h<1", 
      "trp": "h<3"
    }, 
    "Melita": {
      "tup": "h<2", 
      "trp": "h<2"
    }, 
    "Revkah": {
      "tup": "h>1", 
      "trp": "h=2"
    }, 
    "Bab": {
      "tup": "h>3", 
      "trp": "h=2"
    }, 
    "Drusie": {
      "tup": "h>1", 
      "trp": "h>3"
    }, 
    "Gracia": {
      "tup": "h<3", 
      "trp": "h>3"
    }
  }
}